experiment2/decoder24/decoder24.sv
module decoder24(
	input[1:0]x,
	input en,
	output reg [3:0]y
	);
	always@(*)
	begin
		if(en)begin
			case(x)
				2'b00:y=4'b0000;
				2'b01:y=4'b0010;
				2'b10:y=4'b0100;
				2'b11:y=4'b1000;
			endcase
		end
		else
			y=4'b0000;

	end
	endmodule

experiment2/decoder24/dump.vcd
$version Generated by VerilatedVcd $end
$timescale 1s $end

 $scope module TOP $end
  $var wire  1 $ en $end
  $var wire  2 # x [1:0] $end
  $var wire  4 % y [3:0] $end
  $scope module decoder24 $end
   $var wire  1 $ en $end
   $var wire  2 # x [1:0] $end
   $var wire  4 % y [3:0] $end
  $upscope $end
 $upscope $end
$enddefinitions $end


#1
b00 #
0$
b0000 %
#2
b01 #
#3
b10 #
#4
b11 #
#5
b00 #
1$
#6
b01 #
b0010 %
#7
b10 #
b0100 %
#8
b11 #
b1000 %
